{
    "SmartAgent": {
        "checkpoints": [
            {
                "steps": 22023,
                "file_path": "results/11/SmartAgent/SmartAgent-22023.onnx",
                "reward": null,
                "creation_time": 1637763123.266347,
                "auxillary_file_paths": [
                    "results/11/SmartAgent/SmartAgent-22023.pt"
                ]
            }
        ],
        "final_checkpoint": {
            "steps": 22023,
            "file_path": "results/11/SmartAgent.onnx",
            "reward": null,
            "creation_time": 1637763123.266347,
            "auxillary_file_paths": [
                "results/11/SmartAgent/SmartAgent-22023.pt"
            ]
        }
    },
    "metadata": {
        "stats_format_version": "0.3.0",
        "mlagents_version": "0.27.0",
        "torch_version": "1.8.1"
    }
}